pulpcore/cli/ostree/__init__.py
pulpcore/cli/ostree/distribution.py
pulpcore/cli/ostree/py.typed
pulpcore/cli/ostree/remote.py
pulpcore/cli/ostree/repository.py
pulp_cli_ostree-0.6.0.dist-info/METADATA
pulp_cli_ostree-0.6.0.dist-info/WHEEL
pulp_cli_ostree-0.6.0.dist-info/entry_points.txt
pulp_cli_ostree-0.6.0.dist-info/top_level.txt
pulp_cli_ostree-0.6.0.dist-info/RECORD
