Metadata-Version: 2.1
Name: pulp-cli-ostree
Version: 0.6.0
Summary: Command line interface to talk to pulpcore's REST API. (OSTree plugin commands)
Author-email: Pulp Team <pulp-list@redhat.com>
License: GPLv2+
Project-URL: repository, https://github.com/pulp/pulp-cli-ostree
Project-URL: changelog, https://github.com/pulp/pulp-cli-ostree/blob/main/CHANGES.md
Classifier: Development Status :: 4 - Beta
Classifier: Environment :: Console
Classifier: Intended Audience :: System Administrators
Classifier: License :: OSI Approved :: GNU General Public License v2 or later (GPLv2+)
Classifier: Operating System :: OS Independent
Classifier: Programming Language :: Python :: 3
Classifier: Topic :: System :: Software Distribution
Classifier: Typing :: Typed
Requires-Python: >=3.9
Requires-Dist: pulp-cli<0.36,>=0.23.1
Requires-Dist: pulp-glue-ostree==0.6.0
